ai_code_analyzer/__init__.py
ai_code_analyzer-1.0.1.dist-info/licenses/LICENSE
core/__init__.py
core/ai_model.py
core/analyzer.py
core/github_integration.py
core/load_tester.py
core/release_notes.py
core/test_executor.py
utils/__init__.py
utils/config.py
utils/logger.py
ai_code_analyzer-1.0.1.dist-info/METADATA
ai_code_analyzer-1.0.1.dist-info/WHEEL
ai_code_analyzer-1.0.1.dist-info/entry_points.txt
ai_code_analyzer-1.0.1.dist-info/top_level.txt
ai_code_analyzer-1.0.1.dist-info/RECORD
