Metadata-Version: 2.4
Name: ai-code-analyzer
Version: 1.0.1
Summary: AI-powered code analysis tool for CI/CD pipelines with GitHub Actions integration
Home-page: https://github.com/ai-code-analyzer/ai-code-analyzer
Author: AI Code Analysis Team
Author-email: AI Code Analysis Team <team@ai-code-analyzer.com>
Maintainer-email: AI Code Analysis Team <team@ai-code-analyzer.com>
License: MIT License
Project-URL: Homepage, https://github.com/ai-code-analyzer/ai-code-analyzer
Project-URL: Documentation, https://ai-code-analyzer.readthedocs.io/
Project-URL: Repository, https://github.com/ai-code-analyzer/ai-code-analyzer
Project-URL: Bug Tracker, https://github.com/ai-code-analyzer/ai-code-analyzer/issues
Project-URL: Changelog, https://github.com/ai-code-analyzer/ai-code-analyzer/blob/main/CHANGELOG.md
Keywords: ai,code-analysis,ci-cd,github-actions,testing,security,performance
Classifier: Development Status :: 5 - Production/Stable
Classifier: Intended Audience :: Developers
Classifier: Topic :: Software Development :: Quality Assurance
Classifier: Topic :: Software Development :: Testing
Classifier: License :: OSI Approved :: MIT License
Classifier: Programming Language :: Python :: 3
Classifier: Programming Language :: Python :: 3.8
Classifier: Programming Language :: Python :: 3.9
Classifier: Programming Language :: Python :: 3.10
Classifier: Programming Language :: Python :: 3.11
Classifier: Programming Language :: Python :: 3.12
Classifier: Operating System :: OS Independent
Requires-Python: >=3.8
License-File: LICENSE
Requires-Dist: openai>=1.12.0
Requires-Dist: anthropic>=0.18.1
Requires-Dist: requests>=2.31.0
Requires-Dist: PyYAML>=6.0.1
Requires-Dist: gitpython>=3.1.41
Requires-Dist: pytest>=7.4.4
Requires-Dist: pytest-cov>=4.1.0
Requires-Dist: pytest-xdist>=3.5.0
Requires-Dist: aiohttp>=3.8.0
Requires-Dist: click>=8.0.0
Requires-Dist: rich>=13.0.0
Requires-Dist: jinja2>=3.0.0
Provides-Extra: dev
Requires-Dist: pytest>=7.0.0; extra == "dev"
Requires-Dist: pytest-cov>=4.0.0; extra == "dev"
Requires-Dist: black>=23.0.0; extra == "dev"
Requires-Dist: isort>=5.0.0; extra == "dev"
Requires-Dist: flake8>=6.0.0; extra == "dev"
Requires-Dist: mypy>=1.0.0; extra == "dev"
Requires-Dist: pre-commit>=3.0.0; extra == "dev"
Provides-Extra: all
Requires-Dist: pylint>=3.0.0; extra == "all"
Requires-Dist: bandit>=1.7.0; extra == "all"
Requires-Dist: safety>=2.0.0; extra == "all"
Requires-Dist: semgrep>=1.0.0; extra == "all"
Requires-Dist: locust>=2.0.0; extra == "all"
Requires-Dist: radon>=6.0.0; extra == "all"
Requires-Dist: mccabe>=0.7.0; extra == "all"
Requires-Dist: vulture>=2.10; extra == "all"
Dynamic: author
Dynamic: home-page
Dynamic: license-file
Dynamic: requires-python
